{
  "year": 2026,
  "channels": {
    "@AniOneThailand": {
      "channelId": "UCw2bdNSXh4x6e0NCduVoxMQ",
      "uploadsPlaylistId": "UUw2bdNSXh4x6e0NCduVoxMQ",
      "lastSeenVideoId": "nei-0mBq7Lc",
      "lastCheckedAt": "2026-07-07T08:46:48.270Z",
      "year": 2026
    },
    "@MuseThailand": {
      "channelId": "UCn8hjQOnGYR1AZtYYMYP5jQ",
      "uploadsPlaylistId": "UUn8hjQOnGYR1AZtYYMYP5jQ",
      "lastSeenVideoId": "k1dUAn_4rHc",
      "lastCheckedAt": "2026-07-07T08:46:47.017Z",
      "year": 2026
    },
    "@TropicsAnimeAsia": {
      "channelId": "UCC-g5hWSvCbdB8HQQIA0_pg",
      "uploadsPlaylistId": "UUC-g5hWSvCbdB8HQQIA0_pg",
      "lastSeenVideoId": "1yQpRqutnBw",
      "lastCheckedAt": "2026-07-07T08:46:48.719Z",
      "year": 2026
    },
    "@ItsAnimeJP": {
      "channelId": "UCsj_CYajUSQ2ca8bYCMan9g",
      "uploadsPlaylistId": "UUsj_CYajUSQ2ca8bYCMan9g",
      "lastSeenVideoId": "bztYaH6hbxg",
      "lastCheckedAt": "2026-07-07T08:46:49.020Z",
      "year": 2026
    }
  }
}
