{
  "year": 2026,
  "channels": {
    "@AniOneThailand": {
      "channelId": "UCw2bdNSXh4x6e0NCduVoxMQ",
      "uploadsPlaylistId": "UUw2bdNSXh4x6e0NCduVoxMQ",
      "lastSeenVideoId": "QOw480jFFdA",
      "lastCheckedAt": "2026-07-11T17:18:52.489Z",
      "year": 2026
    },
    "@MuseThailand": {
      "channelId": "UCn8hjQOnGYR1AZtYYMYP5jQ",
      "uploadsPlaylistId": "UUn8hjQOnGYR1AZtYYMYP5jQ",
      "lastSeenVideoId": "Zqc0JE8vsTI",
      "lastCheckedAt": "2026-07-11T17:18:50.974Z",
      "year": 2026
    },
    "@TropicsAnimeAsia": {
      "channelId": "UCC-g5hWSvCbdB8HQQIA0_pg",
      "uploadsPlaylistId": "UUC-g5hWSvCbdB8HQQIA0_pg",
      "lastSeenVideoId": "91ZcqNzNR1k",
      "lastCheckedAt": "2026-07-11T17:18:52.939Z",
      "year": 2026
    },
    "@ItsAnimeJP": {
      "channelId": "UCsj_CYajUSQ2ca8bYCMan9g",
      "uploadsPlaylistId": "UUsj_CYajUSQ2ca8bYCMan9g",
      "lastSeenVideoId": "u7Wze_q0eQg",
      "lastCheckedAt": "2026-07-11T17:18:53.458Z",
      "year": 2026
    }
  }
}
